cdk_monitoring_constructs/__init__.py
cdk_monitoring_constructs/py.typed
cdk_monitoring_constructs/_jsii/__init__.py
cdk_monitoring_constructs/_jsii/cdk-monitoring-constructs@9.15.2.jsii.tgz
cdk_monitoring_constructs-9.15.2.dist-info/LICENSE
cdk_monitoring_constructs-9.15.2.dist-info/METADATA
cdk_monitoring_constructs-9.15.2.dist-info/NOTICE
cdk_monitoring_constructs-9.15.2.dist-info/WHEEL
cdk_monitoring_constructs-9.15.2.dist-info/top_level.txt
cdk_monitoring_constructs-9.15.2.dist-info/RECORD
