Metadata-Version: 2.1
Name: cdk-monitoring-constructs
Version: 9.15.2
Summary: cdk-monitoring-constructs
Home-page: https://github.com/cdklabs/cdk-monitoring-constructs
Author: CDK Monitoring Constructs Team<monitoring-cdk-constructs@amazon.com>
License: Apache-2.0
Project-URL: Source, https://github.com/cdklabs/cdk-monitoring-constructs
Classifier: Intended Audience :: Developers
Classifier: Operating System :: OS Independent
Classifier: Programming Language :: JavaScript
Classifier: Programming Language :: Python :: 3 :: Only
Classifier: Programming Language :: Python :: 3.8
Classifier: Programming Language :: Python :: 3.9
Classifier: Programming Language :: Python :: 3.10
Classifier: Programming Language :: Python :: 3.11
Classifier: Typing :: Typed
Classifier: Development Status :: 4 - Beta
Classifier: License :: OSI Approved
Requires-Python: ~=3.8
License-File: LICENSE
License-File: NOTICE
Requires-Dist: aws-cdk-lib<3.0.0,>=2.160.0
Requires-Dist: constructs<11.0.0,>=10.0.5
Requires-Dist: jsii<2.0.0,>=1.106.0
Requires-Dist: publication>=0.0.3
Requires-Dist: typeguard<4.3.0,>=2.13.3
